utils/__init__.py
utils/pypi_api.py
utils/version_checker.py
vast.py
vast_cli_fork-1.11.90.dist-info/LICENSE
vast_cli_fork-1.11.90.dist-info/METADATA
vast_cli_fork-1.11.90.dist-info/WHEEL
vast_cli_fork-1.11.90.dist-info/entry_points.txt
vast_cli_fork-1.11.90.dist-info/RECORD
